mysite/mysite/__init__.py
mysite/mysite/settings.py
mysite/mysite/urls.py
mysite/mysite/wsgi.py
mysite/polls/__init__.py
mysite/polls/admin.py
mysite/polls/apps.py
mysite/polls/models.py
mysite/polls/tests.py
mysite/polls/urls.py
mysite/polls/views.py
mysite/polls/migrations/0001_initial.py
mysite/polls/migrations/__init__.py
os_sys/__init__.py
os_sys/__main__.py
os_sys/_progress.py
os_sys/datetime_lib.py
os_sys/discription.py
os_sys/doc.html
os_sys/download.py
os_sys/errors.py
os_sys/fail.py
os_sys/func_tools.py
os_sys/install.py
os_sys/mail.py
os_sys/maths.py
os_sys/modules.py
os_sys/os_sys-1.5.3-py3-none-any.whl
os_sys/os_sys.py
os_sys/os_sys_install_upgrade_program(for windows).EXE
os_sys/progress_bars.py
os_sys/re_installer(for windows).EXE
os_sys/script.php
os_sys/server.py
os_sys/system.py
os_sys/test.py
os_sys/test.txt
os_sys/time_lib.py
os_sys/upload.py
os_sys/wifi.py
os_sys/commands/__init__.py
os_sys/commands/credits.data
os_sys/commands/credits.date
os_sys/commands/download.py
os_sys/commands/fail.py
os_sys/commands/install_libs.py
os_sys/commands/license.txt
os_sys/commands/modules.py
os_sys/commands/os_sys.py
os_sys/commands/settings.config
os_sys/commands/system.py
os_sys/commands/test.txt
os_sys/commands/wifi.py
os_sys/commands/data_files/data.os_sys.lib.python.file.include.license.data
os_sys/commands/data_files/info.data
os_sys/commands/programs/__init__.py
os_sys/commands/programs/fail.py
os_sys/commands/test/__test__.py
os_sys/commands/test/bug_log.txt
os_sys/core/downloader.SED
os_sys/core/setup.py
os_sys/data_files/files.data
os_sys/data_files/lib_data.set
os_sys/data_files/wifi_test.data
os_sys/data_files/data/__init__.py
os_sys/data_files/data/files.data
os_sys/data_files/data/wifi_test.data
os_sys/devserver/__init__.py
os_sys/devserver/build.py
os_sys/devserver/db.py
os_sys/devserver/mail.py
os_sys/devserver/server.py
os_sys/devserver/site_db.os_sys_db
os_sys/devserver/testt.py
os_sys/devserver/core/__init__.py
os_sys-1.7.1.dist-info/LICENSE.txt
os_sys-1.7.1.dist-info/METADATA
os_sys-1.7.1.dist-info/WHEEL
os_sys-1.7.1.dist-info/entry_points.txt
os_sys-1.7.1.dist-info/top_level.txt
os_sys-1.7.1.dist-info/RECORD
