Metadata-Version: 2.1
Name: os-sys
Version: 1.7.1
Summary: a big lib with many usefull tools and it are not only os and sys tools...
Home-page: https://stranica.nl/
Author: Matthijs labots
Author-email: py.libs@gmail.com
License: GNU General Public License
Project-URL: all files, https://github.com/Matthijs990/os_sys
Project-URL: Downloads, https://stranica.nl/downloads.html
Project-URL: download all files, https://github.com/Matthijs990/os_sys.git
Project-URL: want to help, https://github.com/Matthijs990/os_sys/tree/master/do%20you%20want%20to%20help
Project-URL: startpage, https://pypi.org/project/os-sys/
Project-URL: made possible by, https://pypi.org
Project-URL: help, https://github.com/Matthijs990/os_sys/issues
Project-URL: github wiki(under development), https://github.com/Matthijs990/os_sys/wiki
Project-URL: just a chat to talk about python, https://github.com/Matthijs990/chat/issues/1
Project-URL: github, https://github.com/Matthijs990/os_sys
Project-URL: os_sys online, https://stranica.nl/os_sys/
Project-URL: gitlab, https://gitlab.com/Matthijs990/os_sys
Project-URL: read the docs, https://os-sys-wiki-page.readthedocs.io/en/latest/index.html
Platform: UNKNOWN
Classifier: Programming Language :: Python :: 3
Classifier: License :: OSI Approved :: MIT License
Classifier: Operating System :: OS Independent
Classifier: Topic :: Software Development :: Libraries :: Python Modules
Classifier: Framework :: IDLE
Classifier: Natural Language :: Dutch
Classifier: Natural Language :: English
Classifier: Programming Language :: Python :: 3.0
Classifier: Programming Language :: Python :: 3.1
Classifier: Programming Language :: Python :: 3.2
Classifier: Programming Language :: Python :: 3.3
Classifier: Programming Language :: Python :: 3.4
Classifier: Programming Language :: Python :: 3.5
Classifier: Programming Language :: Python :: 3.6
Classifier: Programming Language :: Python :: 3.7
Classifier: Programming Language :: Python
Classifier: Topic :: Internet
Classifier: Topic :: Other/Nonlisted Topic
Classifier: Topic :: Scientific/Engineering :: Mathematics
Classifier: Topic :: Scientific/Engineering :: Visualization
Classifier: Topic :: Software Development :: Build Tools
Classifier: Topic :: Software Development :: User Interfaces
Classifier: Topic :: Software Development
Classifier: Topic :: Scientific/Engineering
Classifier: Topic :: Desktop Environment :: File Managers
Classifier: Topic :: Internet
Classifier: Topic :: Internet :: File Transfer Protocol (FTP)
Classifier: Topic :: Internet :: WWW/HTTP
Classifier: Topic :: Software Development :: Libraries
Classifier: Topic :: Software Development :: Testing
Classifier: Topic :: System
Classifier: Topic :: Software Development :: Testing
Classifier: Topic :: System :: Operating System
Classifier: Development Status :: 4 - Beta
Classifier: Development Status :: 5 - Production/Stable
Classifier: Framework :: Django :: 2.2
Classifier: Framework :: Django
Classifier: Topic :: Documentation
Classifier: Topic :: Security :: Cryptography
Classifier: Topic :: Software Development :: Code Generators
Classifier: Topic :: Software Development :: Compilers
Classifier: Topic :: System
Classifier: Topic :: System :: Installation/Setup
Classifier: Topic :: System :: Software Distribution
Classifier: Topic :: Text Processing :: Markup :: HTML
Requires-Python: >=3
Requires-Dist: progress
Requires-Dist: tqdm
Requires-Dist: progressbar
Requires-Dist: matplotlib
Requires-Dist: numpy
Requires-Dist: jupyter
Requires-Dist: pandas
Requires-Dist: beautifulsoup4
Requires-Dist: Eel
Requires-Dist: extract-zip
Requires-Dist: text-editor
Requires-Dist: tuspy
Requires-Dist: requests-download
Requires-Dist: requests
Requires-Dist: Send2Trash
Requires-Dist: pyspeedtest
Requires-Dist: pytest
Requires-Dist: wifi
Requires-Dist: PyInstaller
Requires-Dist: auto-py-to-exe
Requires-Dist: Django
Requires-Dist: mysql-connector
Requires-Dist: geocoder
Requires-Dist: selenium
Requires-Dist: psutil
Requires-Dist: pynput
